LICENSE
MANIFEST.in
README.md
setup.cfg
setup.py
bin/uuid64
uuid64/__init__.py
uuid64/uuid64.py
uuid64.egg-info/PKG-INFO
uuid64.egg-info/SOURCES.txt
uuid64.egg-info/dependency_links.txt
uuid64.egg-info/top_level.txt