Metadata-Version: 1.1
Name: uuid64
Version: 0.1.1
Summary: Generate 64bit UUIDs
Home-page: http://github.com/jdowner/uuid64
Author: Joshua Downer
Author-email: joshua.downer@gmail.com
License: MIT
Keywords: uuid 64bit
Platform: Unix
Classifier: Development Status :: 3 - Alpha
Classifier: Environment :: Console
Classifier: Intended Audience :: Developers
Classifier: Intended Audience :: End Users/Desktop
Classifier: Intended Audience :: System Administrators
Classifier: License :: OSI Approved :: MIT License
Classifier: Operating System :: POSIX
Classifier: Programming Language :: Python
Classifier: Programming Language :: Python :: 2
Classifier: Programming Language :: Python :: 2.7
Classifier: Programming Language :: Python :: 3
Classifier: Programming Language :: Python :: 3.3
Classifier: Programming Language :: Python :: 3.4
Classifier: Topic :: System :: Shells
Classifier: Topic :: System :: Systems Administration
Classifier: Topic :: System :: System Shells
Classifier: Topic :: Utilities
